{
  "users": [
    {
      "id": "1",
      "username": "johndoe",
      "password": "password",
      "email": "johndoe@me.com"
    },
    {
      "id": "2",
      "username": "janedoe",
      "password": "password",
      "email": "janedoe@me.com"
    }
  ],
  "tasks": [
    {
      "id": "1",
      "title": "Task 1",
      "description": "Task 1 description",
      "isDone": true,
      "userId": 1
    },
    {
      "id": "2",
      "title": "Task 2",
      "description": "Task 2 description",
      "isDone": false,
      "userId": 1
    },
    {
      "id": "3",
      "title": "Task 3",
      "description": "Task 3 description",
      "isDone": false,
      "userId": 2
    },
    {
      "id": "4",
      "title": "Task 4",
      "description": "Task 4 description",
      "isDone": false,
      "userId": 2
    },
    {
      "id": "ab94e34e-f556-4fc1-b7bb-41c7f0323f06",
      "title": "Prueba editada 2",
      "description": "Prueba 2",
      "isDone": false,
      "userId": "1"
    }
  ]
}